[
    {
        "Email": "admin@admin.com",
        "UserName": "admin@admin.com",
        "FirstName": "Admin",
        "LastName": "Admin",
        "Address": "Admin",
        "ProfileImg": "images/user-icon-2098873_960_720.png",
        "AreasOfExpertise": "Admin",
        "UserType": "IsAdmin",
        "EmailConfirmed": true,
        "PhoneNumber": "0X0XXXX999",
        "PhoneNumberConfirmed": true
    },
    {
        "Email": "headmaster@headmaster.com",
        "UserName": "headmaster@headmaster.com",
        "FirstName": "Headmaster",
        "LastName": "Headmaster",
        "Address": "Headmaster",
        "ProfileImg": "images/user-icon-2098873_960_720.png",
        "AreasOfExpertise": "Headmaster",
        "UserType": "IsHeadmaster",
        "EmailConfirmed": true,
        "PhoneNumber": "0X0XXXX999",
        "PhoneNumberConfirmed": true
    },
    {
        "Email": "teacher@teacher.com",
        "UserName": "teacher@teacher.com",
        "FirstName": "Teacher",
        "LastName": "Teacher",
        "Address": "Teacher",
        "ProfileImg": "images/user-icon-2098873_960_720.png",
        "AreasOfExpertise": "Teacher",
        "UserType": "IsTeacher",
        "EmailConfirmed": true,
        "PhoneNumber": "0X0XXXX999",
        "PhoneNumberConfirmed": true
    },
    {
        "Email": "student@student.com",
        "UserName": "student@student.com",
        "FirstName": "Student",
        "LastName": "Student",
        "Address": "Student",
        "ProfileImg": "images/user-icon-2098873_960_720.png",
        "AreasOfExpertise": "Student",
        "UserType": "IsStudent",
        "EmailConfirmed": true,
        "PhoneNumber": "0X0XXXX999",
        "PhoneNumberConfirmed": true
    },
    {
        "Email": "user@user.com",
        "UserName": "user@user.com",
        "FirstName": "User",
        "LastName": "User",
        "Address": "User",
        "ProfileImg": "images/user-icon-2098873_960_720.png",
        "AreasOfExpertise": "User",
        "UserType": "IsUser",
        "EmailConfirmed": true,
        "PhoneNumber": "0X0XXXX999",
        "PhoneNumberConfirmed": true
    }
]